birria/__init__.py
birria/_birria.py
birria-0.2.3.dist-info/LICENSE
birria-0.2.3.dist-info/METADATA
birria-0.2.3.dist-info/WHEEL
birria-0.2.3.dist-info/top_level.txt
birria-0.2.3.dist-info/RECORD
